gcm_diagnostics/__init__.py
gcm_diagnostics/collector.py
gcm_diagnostics/errors.py
gcm_diagnostics/exception.py
gcm_diagnostics/handler.py
gcm_diagnostics/models.py
gcm_diagnostics/py.typed
gcm_diagnostics-1.4.1.dist-info/LICENSE
gcm_diagnostics-1.4.1.dist-info/METADATA
gcm_diagnostics-1.4.1.dist-info/WHEEL
gcm_diagnostics-1.4.1.dist-info/RECORD
