Metadata-Version: 2.1
Name: gcm-diagnostics
Version: 1.4.1
Summary: Business validation diagnostics (errors) collection library. With FastAPI support.
Author: Michal Kuchta
Author-email: niximor@gmail.com
Requires-Python: >=3.11,<4.0
Classifier: Development Status :: 5 - Production/Stable
Classifier: Intended Audience :: Developers
Classifier: License :: OSI Approved :: MIT License
Classifier: Operating System :: OS Independent
Classifier: Programming Language :: Python :: 3
Classifier: Programming Language :: Python :: 3.11
Classifier: Programming Language :: Python :: 3.12
Classifier: Topic :: Software Development :: Libraries
Requires-Dist: fastapi (>=0,<1)
Requires-Dist: pydantic (>=2,<3)
Project-URL: Homepage, https://gitlab.com/gcm-cz/gcm-diagnostics
Project-URL: Issues, https://gitlab.com/gcm-cz/gcm-diagnostics/-/issues
Project-URL: Repository, https://gitlab.com/gcm-cz/gcm-diagnostics
